{
  "kind": "singleType",
  "collectionName": "main_ads",
  "info": {
    "name": "mainAd"
  },
  "options": {
    "increments": true,
    "timestamps": true,
    "draftAndPublish": true
  },
  "attributes": {
    "description": {
      "type": "richtext"
    },
    "title": {
      "type": "string"
    },
    "images": {
      "collection": "file",
      "via": "related",
      "allowedTypes": [
        "images",
        "files",
        "videos"
      ],
      "plugin": "upload",
      "required": false
    }
  }
}
